LICENSE
MANIFEST.in
README.rst
setup.cfg
setup.py
cms_forms.egg-info/PKG-INFO
cms_forms.egg-info/SOURCES.txt
cms_forms.egg-info/dependency_links.txt
cms_forms.egg-info/not-zip-safe
cms_forms.egg-info/top_level.txt
forms/__init__.py
forms/admin.py
forms/apps.py
forms/inlines.py
forms/models.py
forms/schema.py
forms/api/APIException.py
forms/api/Form.py
forms/api/User.py
forms/api/ViewEntries.py
forms/api/__init__.py