Metadata-Version: 1.2
Name: cms-forms
Version: 0.1.2
Summary: CMS plugin for creating and managing forms
Home-page: https://www.rivivo.xyz/projects/cms
Author: Ashwin Shenoy
Author-email: aswinshenoy65@gmail.com
Maintainer: Ashwin Shenoy
Maintainer-email: aswinshenoy65@gmail.com
License: GNU-GPL-V3
Platform: UNKNOWN
Classifier: Environment :: Web Environment
Classifier: Intended Audience :: Developers
Classifier: Development Status :: 2 - Pre-Alpha
Classifier: License :: OSI Approved :: GNU General Public License v3 (GPLv3)
Classifier: Operating System :: OS Independent
Classifier: Programming Language :: Python
Classifier: Programming Language :: Python :: 3
Classifier: Programming Language :: Python :: 3.4
Classifier: Programming Language :: Python :: 3.5
Classifier: Programming Language :: Python :: 3.6
Classifier: Programming Language :: Python :: 3.7
Classifier: Programming Language :: Python :: 3.8
Classifier: Framework :: Django
Classifier: Framework :: Django :: 2.2
Classifier: Topic :: Internet :: WWW/HTTP
Classifier: Topic :: Internet :: WWW/HTTP :: Dynamic Content
